turbojet/__init__.py
turbojet/turbojet.py
nazwa_biblioteki-0.0.1.dist-info/LICENSE
nazwa_biblioteki-0.0.1.dist-info/METADATA
nazwa_biblioteki-0.0.1.dist-info/WHEEL
nazwa_biblioteki-0.0.1.dist-info/top_level.txt
nazwa_biblioteki-0.0.1.dist-info/RECORD
