Metadata-Version: 2.1
Name: nazwa-biblioteki
Version: 0.0.1
Summary: Opis biblioteki
Home-page: https://github.com/JakUrb04/turbojet.git
Author: Jakub Urbaniak
Author-email: urbaniak627@gmail.com
License: MIT
Platform: UNKNOWN
Classifier: Development Status :: 3 - Alpha
Classifier: Intended Audience :: Developers
Classifier: Programming Language :: Python :: 3
Classifier: Programming Language :: Python :: 3.6
Classifier: Programming Language :: Python :: 3.7
Classifier: Programming Language :: Python :: 3.8
Classifier: Programming Language :: Python :: 3.9
